cppt/__init__.py
cppt/cli.py
cppt/config.py
cppt/record.py
cppt/version.py
paddle_cppt-0.0.1.dist-info/LICENSE
paddle_cppt-0.0.1.dist-info/METADATA
paddle_cppt-0.0.1.dist-info/WHEEL
paddle_cppt-0.0.1.dist-info/entry_points.txt
paddle_cppt-0.0.1.dist-info/top_level.txt
paddle_cppt-0.0.1.dist-info/RECORD
