Metadata-Version: 2.1
Name: paddle-cppt
Version: 0.0.1
Summary: UNKNOWN
Home-page: https://github.com/wj-Mcat/paddle-cppt
Author: Jingjing WU (吴京京)
Author-email: wjmcater@gmail.com
License: Apache-2.0
Platform: UNKNOWN
Classifier: Programming Language :: Python :: 3.7
Classifier: License :: OSI Approved :: Apache Software License
Classifier: Operating System :: OS Independent
Requires-Dist: dataclasses-json
Requires-Dist: tabulate
